gnpy/__init__.py
gnpy/core/__init__.py
gnpy/core/ansi_escapes.py
gnpy/core/elements.py
gnpy/core/equipment.py
gnpy/core/exceptions.py
gnpy/core/info.py
gnpy/core/network.py
gnpy/core/parameters.py
gnpy/core/science_utils.py
gnpy/core/utils.py
gnpy/example-data/CORONET_CONUS_Topology.json
gnpy/example-data/CORONET_Global_Topology.json
gnpy/example-data/CORONET_Global_Topology.xls
gnpy/example-data/Juniper-BoosterHG.json
gnpy/example-data/Sweden_OpenROADMv4_example_network.json
gnpy/example-data/Sweden_OpenROADMv5_example_network.json
gnpy/example-data/create_eqpt_sheet.py
gnpy/example-data/edfa_example_network.json
gnpy/example-data/eqpt_config.json
gnpy/example-data/eqpt_config_multiband.json
gnpy/example-data/eqpt_config_openroadm_ver4.json
gnpy/example-data/eqpt_config_openroadm_ver5.json
gnpy/example-data/extra_eqpt_config.json
gnpy/example-data/fused_roadm_example_network.json
gnpy/example-data/initial_spectrum1.json
gnpy/example-data/initial_spectrum2.json
gnpy/example-data/juniperTopologyExampleV2J.xls
gnpy/example-data/meshTopologyExampleV2.json
gnpy/example-data/meshTopologyExampleV2.xls
gnpy/example-data/meshTopologyExampleV2_services.json
gnpy/example-data/multiband_example_network.json
gnpy/example-data/multiband_spectrum.json
gnpy/example-data/raman_edfa_example_network.json
gnpy/example-data/service_pluggable.json
gnpy/example-data/sim_params.json
gnpy/example-data/std_medium_gain_advanced_config.json
gnpy/example-data/edfa_model/DFG_96.txt
gnpy/example-data/edfa_model/DGT_96.txt
gnpy/example-data/edfa_model/NFR_96.txt
gnpy/example-data/edfa_model/OA.json
gnpy/example-data/edfa_model/build_oa_json.py
gnpy/example-data/edfa_model/pNFfit3.txt
gnpy/tools/__init__.py
gnpy/tools/cli_examples.py
gnpy/tools/convert.py
gnpy/tools/convert_legacy_yang.py
gnpy/tools/create_eqpt_sheet.py
gnpy/tools/default_edfa_config.py
gnpy/tools/json_io.py
gnpy/tools/plots.py
gnpy/tools/service_sheet.py
gnpy/tools/worker_utils.py
gnpy/tools/write_path_jsontocsv.py
gnpy-2.13.0.dist-info/licenses/AUTHORS.rst
gnpy-2.13.0.dist-info/licenses/LICENSE
gnpy-2.13.0.dist-info/METADATA
gnpy-2.13.0.dist-info/WHEEL
gnpy-2.13.0.dist-info/entry_points.txt
gnpy-2.13.0.dist-info/pbr.json
gnpy-2.13.0.dist-info/top_level.txt
gnpy-2.13.0.dist-info/RECORD
