Metadata-Version: 2.4
Name: gnpy
Version: 2.13.0
Home-page: https://github.com/Telecominfraproject/oopt-gnpy
Author: Telecom Infra Project
Author-email: jkt@jankundrat.com
License: BSD-3-Clause
Project-URL: Bug Tracker, https://github.com/Telecominfraproject/oopt-gnpy/issues
Project-URL: Documentation, https://gnpy.readthedocs.io/
Keywords: optics,network,fiber,communication,route,planning,optimization
Classifier: Development Status :: 5 - Production/Stable
Classifier: Intended Audience :: Developers
Classifier: Intended Audience :: Science/Research
Classifier: Intended Audience :: Telecommunications Industry
Classifier: License :: OSI Approved :: BSD License
Classifier: Natural Language :: English
Classifier: Programming Language :: Python
Classifier: Programming Language :: Python :: 3 :: Only
Classifier: Programming Language :: Python :: 3.8
Classifier: Programming Language :: Python :: 3.9
Classifier: Programming Language :: Python :: 3.10
Classifier: Programming Language :: Python :: 3.11
Classifier: Programming Language :: Python :: 3.12
Classifier: Programming Language :: Python :: Implementation :: CPython
Classifier: Topic :: Scientific/Engineering
Classifier: Topic :: Scientific/Engineering :: Physics
Classifier: Topic :: System :: Networking
Requires-Python: >=3.8
License-File: LICENSE
License-File: AUTHORS.rst
Requires-Dist: matplotlib<4,>=3.7.3
Requires-Dist: networkx<4,>=3.1
Requires-Dist: numpy<2,>=1.24.4
Requires-Dist: oopt_gnpy_libyang>=0.0.14
Requires-Dist: openpyxl<4,>=3.1.5
Requires-Dist: pbr<7,>=6.0.0
Requires-Dist: scipy<2,>=1.10.1
Requires-Dist: xlrd<3,>=2.0.1
Provides-Extra: tests
Requires-Dist: build<2,>=1.0.3; extra == "tests"
Requires-Dist: pytest<8,>=7.4.3; extra == "tests"
Requires-Dist: pandas<3,>=2.0.3; extra == "tests"
Requires-Dist: flake8<6,>=5.0.4; extra == "tests"
Provides-Extra: docs
Requires-Dist: alabaster<1,>=0.7.12; extra == "docs"
Requires-Dist: docutils<1,>=0.17.1; extra == "docs"
Requires-Dist: myst-parser<5,>=4.0.1; extra == "docs"
Requires-Dist: Pygments<3,>=2.11.2; extra == "docs"
Requires-Dist: rstcheck; extra == "docs"
Requires-Dist: Sphinx<9,>=8.1.3; extra == "docs"
Requires-Dist: sphinxcontrib-bibtex<3,>=2.4.1; extra == "docs"
Requires-Dist: sphinx_rtd_theme<4,>=3.0.2; extra == "docs"
Dynamic: author
Dynamic: author-email
Dynamic: classifier
Dynamic: description
Dynamic: description-content-type
Dynamic: home-page
Dynamic: keywords
Dynamic: license
Dynamic: license-file
Dynamic: project-url
Dynamic: requires-python
